py3comtrade/__init__.py
py3comtrade/computation/__init__.py
py3comtrade/computation/basic_calc.py
py3comtrade/computation/calcium.py
py3comtrade/computation/fourier.py
py3comtrade/computation/impedance.py
py3comtrade/computation/math_polar_rect.py
py3comtrade/computation/power.py
py3comtrade/computation/sequence.py
py3comtrade/computation/zerolocation.py
py3comtrade/dispose/__init__.py
py3comtrade/dispose/channel_name.py
py3comtrade/model/__init__.py
py3comtrade/model/channel_num.py
py3comtrade/model/comtrade.py
py3comtrade/model/comtrade_filter.py
py3comtrade/model/config_header.py
py3comtrade/model/config_sample.py
py3comtrade/model/configure.py
py3comtrade/model/data.py
py3comtrade/model/dmf.py
py3comtrade/model/exceptions.py
py3comtrade/model/harmonic.py
py3comtrade/model/nrate.py
py3comtrade/model/precision_time.py
py3comtrade/model/timemult.py
py3comtrade/model/channel/__init__.py
py3comtrade/model/channel/analog.py
py3comtrade/model/channel/analog_channel.py
py3comtrade/model/channel/channel.py
py3comtrade/model/channel/digital.py
py3comtrade/model/channel/status_channel.py
py3comtrade/model/equipment/__init__.py
py3comtrade/model/equipment/base_param.py
py3comtrade/model/equipment/branch.py
py3comtrade/model/equipment/bus.py
py3comtrade/model/equipment/equipment.py
py3comtrade/model/equipment/line.py
py3comtrade/model/equipment/line_param.py
py3comtrade/model/equipment/transformer.py
py3comtrade/model/type/__init__.py
py3comtrade/model/type/analog_enum.py
py3comtrade/model/type/base_enum.py
py3comtrade/model/type/data_file_type.py
py3comtrade/model/type/digital_enum.py
py3comtrade/model/type/mode_enum.py
py3comtrade/model/type/phase_code.py
py3comtrade/model/type/types.py
py3comtrade/reader/__init__.py
py3comtrade/reader/analog_parser.py
py3comtrade/reader/channel_num_parser.py
py3comtrade/reader/comtrade_reader.py
py3comtrade/reader/config_reader.py
py3comtrade/reader/data_reader.py
py3comtrade/reader/digital_parser.py
py3comtrade/reader/dmf_reader.py
py3comtrade-4.2.2.dist-info/licenses/LICENSE
py3comtrade-4.2.2.dist-info/METADATA
py3comtrade-4.2.2.dist-info/WHEEL
py3comtrade-4.2.2.dist-info/top_level.txt
py3comtrade-4.2.2.dist-info/RECORD
