Metadata-Version: 2.4
Name: py3comtrade
Version: 4.2.2
Summary: 解析comtrade中的cfg、dat、dmf等文件，提供配置文件中通道数量，的解析、数值计算和文件合并功能。
Requires-Python: >=3.10
License-File: LICENSE
Requires-Dist: chardet>=5.2.0
Requires-Dist: numpy>=2.0.0
Requires-Dist: openpyxl>=3.1.5
Requires-Dist: pandas==2.3.3
Requires-Dist: pydantic>=2.11.10
Requires-Dist: pylint>=3.3.8
Requires-Dist: xmltodict>=1.0.2
Dynamic: license-file
